artlogs/__init__.py
artlogs/core.py
artlogs-1.0.0.dist-info/licenses/LICENSE
artlogs-1.0.0.dist-info/METADATA
artlogs-1.0.0.dist-info/WHEEL
artlogs-1.0.0.dist-info/top_level.txt
artlogs-1.0.0.dist-info/RECORD
