Metadata-Version: 2.4
Name: artlogs
Version: 1.0.0
Summary: A beautiful and structured logging library with profile support
Author-email: Na9ash1 <a70655776@gmail.com>
Project-URL: Homepage, https://github.com/yourusername/artlogs
Keywords: logging,profiles,colored,beautiful
Classifier: Programming Language :: Python :: 3
Classifier: License :: OSI Approved :: MIT License
Classifier: Operating System :: OS Independent
Classifier: Topic :: System :: Logging
Classifier: Development Status :: 4 - Beta
Requires-Python: >=3.7
License-File: LICENSE
Requires-Dist: colorama>=0.4.6
Dynamic: license-file
